codebuddy/__init__.py
codebuddy/core.py
codebuddy/helper.py
codebuddy/stackAPI.py
codebuddy-0.0.4.dist-info/LICENSE
codebuddy-0.0.4.dist-info/METADATA
codebuddy-0.0.4.dist-info/WHEEL
codebuddy-0.0.4.dist-info/top_level.txt
codebuddy-0.0.4.dist-info/RECORD
