Metadata-Version: 2.1
Name: codebuddy
Version: 0.0.4
Summary: stack overflow search on exception
Home-page: https://theaarushgupta.com/work/codebuddy
Author: Aarush Gupta
Author-email: aarush@theaarushgupta.com
License: AGPLv3+
Classifier: License :: OSI Approved :: GNU Affero General Public License v3 or later (AGPLv3+)
Classifier: Programming Language :: Python :: 3
Classifier: Programming Language :: Python :: 3.8
License-File: LICENSE
Requires-Dist: requests
